<?xml version="1.0" encoding="koi8-r"?>

<attributes>

    <attr xml:lang="ru" name="name" desc="ФИО" /> 
    <attr xml:lang="en" name="name" desc="Name" />

    <attr xml:lang="ru" name="login" desc="login" /> 
    <attr xml:lang="en" name="login" desc="login" />

    <attr xml:lang="ru" name="email" desc="E-mail" />
    <attr xml:lang="en" name="email" desc="E-mail" />

    <attr xml:lang="ru" name="email_long" desc="Дополнительный e-mail" />
    <attr xml:lang="en" name="email_long" desc="Additional e-mail" />

    <attr xml:lang="ru" name="forward" desc="Forward" />
    <attr xml:lang="en" name="forward" desc="Forward" />

    <attr xml:lang="ru" name="homepage" desc="Домашняя страница" />
    <attr xml:lang="en" name="homepage" desc="Home page" />

    <attr xml:lang="ru" name="interests" desc="Научные интересы" />
    <attr xml:lang="en" name="interests" desc="Interests" />

    <attr xml:lang="ru" name="work_phone" desc="Рабочий телефон" />
    <attr xml:lang="en" name="work_phone" desc="Work phone" />

    <attr xml:lang="ru" name="home_phone" desc="Домашний телефон" />
    <attr xml:lang="en" name="home_phone" desc="Home phone" />

    <attr xml:lang="ru" name="home_address" desc="Домашний адрес" />
    <attr xml:lang="en" name="home_address" desc="Home address" />

    <attr xml:lang="ru" name="admission_date" desc="Дата поступления" />
    <attr xml:lang="en" name="admission_date" desc="Admission date" />

    <attr xml:lang="ru" name="salary" desc="Ставка" />
    <attr xml:lang="en" name="salary" desc="Salary" />

    <attr xml:lang="ru" name="phd_subject" desc="Тема диссертации" />
    <attr xml:lang="en" name="phd_subject" desc="Subject" />

    <attr xml:lang="ru" name="msc_subject" desc="Тема курсовой (диплома)" />
    <attr xml:lang="en" name="phd_subject" desc="Subject" />

    <attr xml:lang="ru" name="supervisor" desc="Научный руководитель" />
    <attr xml:lang="en" name="supervisor" desc="Supervisor" />

    <attr xml:lang="ru" name="group" desc="Группа" />
    <attr xml:lang="en" name="group" desc="Group" />

    <attr xml:lang="ru" name="passport_info" desc="Паспортные данные" />
    <attr xml:lang="en" name="passport_info" desc="Passport info" />

    <attr xml:lang="ru" name="ret_num" 
        desc="Номер свидетельства пенсионного страхования" />
    <attr xml:lang="en" name="ret_num" 
        desc="Retirement insurance number" />

    <attr xml:lang="ru" name="inn" desc="ИНН" />
    <attr xml:lang="en" name="inn" desc="Tax payer number" />

    <attr xml:lang="ru" name="additional_comments" 
        desc="Дополнительные замечания" />
    <attr xml:lang="en" name="additional_comments"
        desc="Additional comments" />

    <attr xml:lang="ru" name="office" desc="Офис" list="office.xml" />
    <attr xml:lang="en" name="office" desc="Office" list="office.xml" />

    <attr xml:lang="ru" name="position" desc="Должность" list="position.xml" />
    <attr xml:lang="en" name="position" desc="Position" list="position.xml" />

    <attr xml:lang="ru" name="degree" desc="Степень" list="degree.xml" />
    <attr xml:lang="en" name="degree" desc="Degree" list="degree.xml" />

    <attr xml:lang="ru" name="rank" desc="Звание" list="rank.xml" />
    <attr xml:lang="en" name="rank" desc="Rank" list="rank.xml" />

    <attr xml:lang="ru" name="staff" desc="Сотрудник" list="staff.xml" />
    <attr xml:lang="en" name="staff" desc="Staff" list="staff.xml" />
    
    <attr xml:lang="ru" name="student" desc="Учащийся" list="student.xml" />
    <attr xml:lang="en" name="student" desc="Student" list="student.xml" />

    <attr xml:lang="ru" name="photo" desc="Фотография" />
    <attr xml:lang="en" name="photo" desc="Photo" />

    <attr xml:lang="ru" name="publications" desc="Список трудов" />
    <attr xml:lang="en" name="publications" desc="Publications" />

    <attr xml:lang="ru" name="mobile_phone" desc="Мобильный телефон" />
    <attr xml:lang="en" name="mobile_phone" desc="Mobile phone" />

    <attr xml:lang="ru" name="pager" desc="Пейджер" />
    <attr xml:lang="en" name="pager" desc="Pager" />

    <attr xml:lang="ru" name="office_hours" desc="Консультация" />
    <attr xml:lang="en" name="office_hours" desc="Office hours" />

    <attr xml:lang="ru" name="videos" desc="Видео" />
    <attr xml:lang="en" name="videos" desc="Videos" />

</attributes>
